Metadata-Version: 1.1
Name: pyphptree
Version: 1.0.3
Summary: UNKNOWN
Home-page: https://github.com/Alexey-T/pyPhpTree
Author: Alexey Torgashin
Author-email: support@uvviewsoft.com
License: UNKNOWN
Platform: UNKNOWN
Classifier: Development Status :: 5 - Production/Stable
Classifier: Programming Language :: Python :: 3
Classifier: Intended Audience :: Developers
Classifier: License :: OSI Approved :: Mozilla Public License 2.0 (MPL 2.0)
Classifier: Operating System :: OS Independent
Classifier: Topic :: Software Development :: Libraries :: Python Modules
